numqi/__init__.py
numqi/_internal.py
numqi/_torch_op.py
numqi/_version.py
numqi/dicke.py
numqi/gellmann.py
numqi/optimal_control.py
numqi/utils.py
numqi/_data/pauli_ud_core.json
numqi/channel/__init__.py
numqi/channel/_gradient_model.py
numqi/channel/_internal.py
numqi/coherence/__init__.py
numqi/coherence/_gradient.py
numqi/coherence/_internal.py
numqi/entangle/_3tangle.py
numqi/entangle/__init__.py
numqi/entangle/_misc.py
numqi/entangle/cha.py
numqi/entangle/concurrence.py
numqi/entangle/distillation.py
numqi/entangle/eof.py
numqi/entangle/measure.py
numqi/entangle/measure_seesaw.py
numqi/entangle/ppt.py
numqi/entangle/pureb.py
numqi/entangle/pureb_quantum.py
numqi/entangle/symext.py
numqi/entangle/upb.py
numqi/gate/__init__.py
numqi/gate/_internal.py
numqi/gate/_pauli.py
numqi/group/__init__.py
numqi/group/_internal.py
numqi/group/_lie.py
numqi/group/_symmetric.py
numqi/group/spf2.py
numqi/group/symext.py
numqi/magic/__init__.py
numqi/magic/_gradient.py
numqi/magic/_internal.py
numqi/magic/_sdp.py
numqi/manifold/_ABk.py
numqi/manifold/__init__.py
numqi/manifold/_compose.py
numqi/manifold/_internal.py
numqi/manifold/_misc.py
numqi/manifold/_stiefel.py
numqi/manifold/plot.py
numqi/matrix_space/__init__.py
numqi/matrix_space/_clebsch_gordan.py
numqi/matrix_space/_concurrence.py
numqi/matrix_space/_geometric_measure.py
numqi/matrix_space/_gradient.py
numqi/matrix_space/_hierarchy.py
numqi/matrix_space/_misc.py
numqi/matrix_space/_numerical_range.py
numqi/matrix_space/_public.py
numqi/maximum_entropy/__init__.py
numqi/maximum_entropy/_internal.py
numqi/maximum_entropy/_model.py
numqi/optimize/__init__.py
numqi/optimize/_internal.py
numqi/qec/__init__.py
numqi/qec/_grad.py
numqi/qec/_internal.py
numqi/qec/_pauli.py
numqi/qec/_qecc.py
numqi/qec/_sdp.py
numqi/qec/_small_code.py
numqi/qec/_varqec.py
numqi/qec/gf4.py
numqi/qec/picode.py
numqi/qec/q623.py
numqi/qec/q723.py
numqi/qec/q823.py
numqi/qec/transversal.py
numqi/query/__init__.py
numqi/query/_gradient_model.py
numqi-0.6.0.dist-info/licenses/LICENSE
numqi-0.6.0.dist-info/METADATA
numqi-0.6.0.dist-info/WHEEL
numqi-0.6.0.dist-info/top_level.txt
numqi-0.6.0.dist-info/RECORD
