Metadata-Version: 2.4
Name: numqi
Version: 0.6.0
Summary: a numpy-based quantum information toolbox
Author-email: husisy <donot@mail.me>
License: GNU Affero General Public License v3.0
Project-URL: Homepage, https://github.com/numqi/numqi/
Project-URL: Documentation, https://numqi.github.io/numqi/
Project-URL: Issues, https://github.com/numqi/numqi/issues
Keywords: quantum information
Classifier: Programming Language :: Python :: 3
Requires-Python: >=3.10
License-File: LICENSE
Requires-Dist: numpy
Requires-Dist: opt_einsum
Requires-Dist: scipy
Requires-Dist: tqdm
Requires-Dist: sympy
Requires-Dist: torch
Requires-Dist: cvxpy
Requires-Dist: matplotlib
Requires-Dist: galois
Requires-Dist: platformdirs
Requires-Dist: h5py
Provides-Extra: dev
Requires-Dist: pytest; extra == "dev"
Requires-Dist: pytest-cov; extra == "dev"
Requires-Dist: pytest-xdist; extra == "dev"
Requires-Dist: mkdocs; extra == "dev"
Requires-Dist: jupyter; extra == "dev"
Requires-Dist: ipywidgets; extra == "dev"
Requires-Dist: mkdocs-material; extra == "dev"
Requires-Dist: mkdocs-jupyter; extra == "dev"
Requires-Dist: pymdown-extensions; extra == "dev"
Requires-Dist: mkdocstrings[python]; extra == "dev"
Requires-Dist: mkdocs-git-revision-date-localized-plugin; extra == "dev"
Requires-Dist: mkdocs-git-authors-plugin; extra == "dev"
Requires-Dist: pyyaml; extra == "dev"
Requires-Dist: build; extra == "dev"
Requires-Dist: twine; extra == "dev"
Dynamic: license-file
